{"stats":{"minecraft:custom":{"minecraft:play_one_minute":3417225,"minecraft:pot_flower":2,"minecraft:leave_game":39,"minecraft:time_since_death":3417109,"minecraft:climb_one_cm":1772,"minecraft:time_since_rest":3417130,"minecraft:sprint_one_cm":3874213,"minecraft:damage_taken":240,"minecraft:walk_one_cm":1559403,"minecraft:drop":3,"minecraft:damage_dealt":36,"minecraft:fly_one_cm":30655534,"minecraft:open_chest":5,"minecraft:crouch_one_cm":128951,"minecraft:deaths":1,"minecraft:sneak_time":111864,"minecraft:walk_under_water_one_cm":3,"minecraft:jump":27085,"minecraft:walk_on_water_one_cm":221984},"minecraft:dropped":{"minecraft:spruce_trapdoor":1,"minecraft:dead_brain_coral_block":1,"minecraft:acacia_door":1},"minecraft:used":{"minecraft:light_blue_carpet":4,"minecraft:purpur_block":1207,"customnpcs:npcscripteddoortool":1,"minecraft:water_bucket":8,"minecraft:jungle_leaves":699,"minecraft:iron_bars":509,"minecraft:acacia_log":7,"minecraft:spruce_door":21,"minecraft:birch_planks":67,"minecraft:oak_planks":386,"minecraft:smooth_quartz_slab":118,"minecraft:polished_andesite":680,"minecraft:stone_shovel":11,"minecraft:spruce_slab":97,"minecraft:acacia_trapdoor":73,"minecraft:polished_blackstone":2,"minecraft:red_nether_bricks":1,"minecraft:jungle_fence":324,"minecraft:ladder":1,"minecraft:andesite_slab":167,"minecraft:polished_basalt":6,"minecraft:spruce_planks":127,"minecraft:chest":8,"chiselsandbits:chiseledgrass":68,"minecraft:white_terracotta":1846,"minecraft:stone":3563,"minecraft:jungle_pressure_plate":17,"minecraft:end_stone_brick_slab":2,"minecraft:stripped_jungle_wood":43,"minecraft:spruce_sign":72,"minecraft:red_nether_brick_stairs":7,"minecraft:warped_sign":2,"minecraft:grass":5,"minecraft:cobblestone_slab":13,"minecraft:purpur_pillar":1146,"minecraft:sandstone_wall":4,"minecraft:structure_block":28,"minecraft:oak_door":2,"minecraft:smooth_quartz_stairs":109,"minecraft:spruce_leaves":80,"minecraft:white_wool":53,"minecraft:purpur_stairs":133,"minecraft:orange_carpet":2,"minecraft:sand":7864,"minecraft:red_nether_brick_slab":105,"minecraft:stripped_dark_oak_log":2,"minecraft:white_carpet":2,"minecraft:oak_slab":17,"minecraft:orange_wool":48,"minecraft:jungle_planks":2592,"minecraft:nether_bricks":23,"minecraft:birch_sign":5,"minecraft:cobblestone_wall":18,"minecraft:jungle_slab":3029,"minecraft:stone_stairs":53,"minecraft:nether_brick_slab":881,"minecraft:warped_door":2,"minecraft:campfire":11,"minecraft:stone_brick_wall":24,"minecraft:painting":6,"minecraft:granite":1208,"minecraft:black_concrete_powder":7,"minecraft:spruce_fence":3,"minecraft:dead_brain_coral_block":6090,"minecraft:nether_brick_stairs":23,"minecraft:dark_oak_door":2,"minecraft:polished_diorite":164,"minecraft:fern":19,"minecraft:birch_door":10,"minecraft:andesite_wall":3,"minecraft:spruce_boat":3,"minecraft:polished_blackstone_slab":4,"minecraft:glass":892,"minecraft:dark_prismarine":38,"minecraft:flower_pot":2,"minecraft:acacia_stairs":32,"minecraft:black_concrete":8,"minecraft:acacia_door":17,"minecraft:stripped_jungle_log":436,"minecraft:light_gray_concrete":31,"minecraft:black_stained_glass_pane":1,"minecraft:iron_block":62,"minecraft:grass_block":5583,"minecraft:acacia_slab":211,"minecraft:stone_button":18,"minecraft:barrier":29,"minecraft:polished_andesite_stairs":59,"minecraft:crimson_slab":1539,"minecraft:jungle_stairs":503,"minecraft:dark_oak_wood":1,"minecraft:stone_slab":35,"minecraft:dark_oak_leaves":399,"minecraft:polished_granite":872,"minecraft:purpur_slab":36,"minecraft:spruce_trapdoor":698,"minecraft:smooth_quartz":104,"minecraft:iron_door":2,"minecraft:crimson_planks":515,"minecraft:acacia_fence_gate":287,"minecraft:item_frame":1,"minecraft:granite_slab":374,"minecraft:jungle_sign":8,"minecraft:glowstone":10,"minecraft:tall_grass":3,"minecraft:cobblestone":11,"minecraft:potion":6,"minecraft:black_stained_glass":3,"minecraft:crimson_door":2,"minecraft:hay_block":712,"minecraft:scaffolding":5,"minecraft:iron_trapdoor":6,"minecraft:jungle_button":2,"minecraft:crimson_stairs":1563,"minecraft:yellow_glazed_terracotta":29,"minecraft:andesite":2716,"minecraft:andesite_stairs":30,"minecraft:bucket":1,"minecraft:jungle_door":2,"minecraft:acacia_fence":1232,"minecraft:acacia_wood":433,"minecraft:smooth_stone_slab":28,"minecraft:polished_blackstone_button":2,"minecraft:stripped_oak_log":98,"minecraft:white_concrete":167,"minecraft:acacia_planks":701,"minecraft:polished_blackstone_stairs":5,"minecraft:brown_mushroom_block":1,"minecraft:smooth_stone":83,"minecraft:large_fern":21},"minecraft:picked_up":{"minecraft:birch_door":7,"minecraft:acacia_door":1,"minecraft:spruce_trapdoor":1,"minecraft:stone_button":2,"minecraft:dead_brain_coral_block":1,"minecraft:spruce_sign":14}},"DataVersion":2586}